MANIFEST.in
changelog.rst
credits.txt
readme.rst
setup.py
DataGridBWC.egg-info/PKG-INFO
DataGridBWC.egg-info/SOURCES.txt
DataGridBWC.egg-info/dependency_links.txt
DataGridBWC.egg-info/not-zip-safe
DataGridBWC.egg-info/requires.txt
DataGridBWC.egg-info/top_level.txt
datagridbwc/__init__.py
datagridbwc/lib/__init__.py
datagridbwc/lib/datagrid.py
datagridbwc/lib/declarative.py
datagridbwc/lib/filters.py
datagridbwc/lib/htmltable.py
datagridbwc/lib/renderers.py
datagridbwc/static/b_firstpage.png
datagridbwc/static/b_lastpage.png
datagridbwc/static/b_nextpage.png
datagridbwc/static/b_prevpage.png
datagridbwc/static/bd_firstpage.png
datagridbwc/static/bd_lastpage.png
datagridbwc/static/bd_nextpage.png
datagridbwc/static/bd_prevpage.png
datagridbwc/static/bullet_toggle_plus.png
datagridbwc/static/sort_down.gif
datagridbwc/static/sort_up.gif
datagridbwc/templates/everything.css
datagridbwc/templates/everything.html
datagridbwc/templates/everything.js
datagridbwc/templates/filter_controls.css
datagridbwc/templates/filter_controls.html
datagridbwc/templates/grid.css
datagridbwc/templates/grid.html
datagridbwc/templates/grid_footer.css
datagridbwc/templates/grid_footer.html
datagridbwc/templates/grid_header.css
datagridbwc/templates/grid_header.html
datagridbwc/templates/grid_header.js
datagridbwc/templates/grid_table.html
datagridbwc/templates/header_filtering.html
datagridbwc/templates/header_paging.html
datagridbwc/templates/header_sorting.html
datagridbwc/templates/pager_controls_lower.css
datagridbwc/templates/pager_controls_lower.html
datagridbwc/templates/pager_controls_upper.css
datagridbwc/templates/pager_controls_upper.html
datagridbwc/templates/sort_controls.css
datagridbwc/templates/sort_controls.html
datagridbwc_ta/.coverage
datagridbwc_ta/__init__.py
datagridbwc_ta/application.py
datagridbwc_ta/views.py
datagridbwc_ta/config/__init__.py
datagridbwc_ta/config/settings.py
datagridbwc_ta/config/site_settings.py
datagridbwc_ta/config/site_settings.py_tpl
datagridbwc_ta/model/__init__.py
datagridbwc_ta/model/orm.py
datagridbwc_ta/static/css/jquery.multiselect.css
datagridbwc_ta/static/js/jquery.multiselect.min.js
datagridbwc_ta/tasks/__init__.py
