Metadata-Version: 1.1
Name: DataGridBWC
Version: 0.2.2
Summary: A BlazeWeb component for turning SQLAlchemy recordsets into HTML tables
Home-page: http://bitbucket.org/blazelibs/datagridbwc/
Author: Randy Syring
Author-email: randy@thesyrings.us
License: BSD
Platform: UNKNOWN
Classifier: Development Status :: 4 - Beta
Classifier: Intended Audience :: Developers
Classifier: License :: OSI Approved :: BSD License
